json_transporter-0.2.2.dist-info/DESCRIPTION.rst
json_transporter-0.2.2.dist-info/entry_points.txt
json_transporter-0.2.2.dist-info/METADATA
json_transporter-0.2.2.dist-info/metadata.json
json_transporter-0.2.2.dist-info/RECORD
json_transporter-0.2.2.dist-info/top_level.txt
json_transporter-0.2.2.dist-info/WHEEL
json_transporter-0.2.2.dist-info/zip-safe
tests/__init__.py
tests/tport_tests.py
transporter/__init__.py
transporter/settings.py
transporter/tools.py
transporter/tport.py
transporter/version.py
