Metadata-Version: 2.0
Name: json-transporter
Version: 0.2.2
Summary: A JSON data transporter
Home-page: https://github.com/istresearch/json-transporter
Author: Jason Haas
Author-email: jasonrhaas@gmail.com
License: MIT
Keywords: json,elasticsearch,s3,kafka,mongo
Platform: UNKNOWN
Classifier: Development Status :: 3 - Alpha
Classifier: Intended Audience :: Developers
Classifier: Topic :: Text Processing :: General
Classifier: License :: OSI Approved :: MIT License
Classifier: Programming Language :: Python :: 2
Classifier: Programming Language :: Python :: 2.6
Classifier: Programming Language :: Python :: 2.7
Requires-Dist: urllib3
Requires-Dist: elasticsearch (>=1.6)
Requires-Dist: boto
Requires-Dist: pymongo
Requires-Dist: happybase
Requires-Dist: pykafka
Requires-Dist: docopt
Provides-Extra: all
Requires-Dist: urllib3; extra == 'all'
Requires-Dist: elasticsearch (>=1.6); extra == 'all'
Requires-Dist: boto; extra == 'all'
Requires-Dist: pymongo; extra == 'all'
Requires-Dist: happybase; extra == 'all'
Requires-Dist: pykafka; extra == 'all'
Requires-Dist: docopt; extra == 'all'
Requires-Dist: nose; extra == 'all'
Provides-Extra: docs
Requires-Dist: sphinx; extra == 'docs'
Requires-Dist: nose; extra == 'docs'
Provides-Extra: lint
Requires-Dist: pep8; extra == 'lint'
Requires-Dist: pyflakes; extra == 'lint'
Provides-Extra: test
Requires-Dist: nose; extra == 'test'
